[
	{
		"title": "The Durban July Cool Dudes",
		"imageUrl": "http://jodyart.co.za/_include/img/work/full/The%20Durban%20July%20Cool%20Dudes.jpg",
		"thumbnailUrl": "http://jodyart.co.za/_include/img/work/thumbs/Dbn-July-Cool-Dudes.jpg",
		"width": 150,
		"height": 100,
		"medium": "oil"
	},
	{
		"title": "Cyclists I",
		"imageUrl": "http://jodyart.co.za/_include/img/work/full/Cyclist1.jpg",
		"thumbnailUrl": "http://jodyart.co.za/_include/img/work/thumbs/Cyclist1.jpg",
		"width": 150,
		"height": 100,
		"medium": "oil"
	},
	{
		"title": "Cyclists II",
		"imageUrl": "http://jodyart.co.za/_include/img/work/full/Cyclist2.jpg",
		"thumbnailUrl": "http://jodyart.co.za/_include/img/work/thumbs/Cyclist2.jpg",
		"width": 150,
		"height": 100,
		"medium": "oil"
	},
	{
		"title": "Kenyan Lady",
		"imageUrl": "http://jodyart.co.za/_include/img/work/full/Kenyan%20Lady.jpg",
		"thumbnailUrl": "http://jodyart.co.za/_include/img/work/thumbs/Kenyan-Lady.jpg",
		"width": 100,
		"height": 120,
		"medium": "oil"
	},
	{
		"title": "Girl with Pearls II",
		"imageUrl": "http://jodyart.co.za/_include/img/work/full/The%20Girl%20with%20the%20pearls%20no.2.jpg",
		"thumbnailUrl": "http://jodyart.co.za/_include/img/work/thumbs/The-Girl-with-the-pearls-no.2.jpg",
		"width": 150,
		"height": 100,
		"medium": "oil"
	},
	{
		"title": "Neon Bikini Girl",
		"imageUrl": "http://jodyart.co.za/_include/img/work/full/Neon-Bikini-Girl.jpg",
		"thumbnailUrl": "http://jodyart.co.za/_include/img/work/thumbs/Neon-Bikini-Girl.jpg",
		"width": 100,
		"height": 120,
		"medium": "oil"
	},
	{
		"title": "Secret Butterfly Tattoo",
		"imageUrl": "http://jodyart.co.za/_include/img/work/full/Secret%20Butterfly%20Tattoo.jpg",
		"thumbnailUrl": "http://jodyart.co.za/_include/img/work/thumbs/Secret-Butterfly-Tattoo.jpg",
		"width": 110,
		"height": 90,
		"medium": "oil"
	},
	{
		"title": "Snake Skin Bikini Girl",
		"imageUrl": "http://jodyart.co.za/_include/img/work/full/Snake%20skin%20Bikini%20girl.jpg",
		"thumbnailUrl": "http://jodyart.co.za/_include/img/work/thumbs/Snake-skin-Bikini-girl.jpg",
		"width": 110,
		"height": 90,
		"medium": "oil"
	},
	{
		"title": "Algarve Girl With Hat",
		"imageUrl": "http://jodyart.co.za/_include/img/work/full/algarve%20girl%20with%20hat.jpg",
		"thumbnailUrl": "http://jodyart.co.za/_include/img/work/thumbs/algarve-girl-with-hat.jpg",
		"width": 80,
		"height": 100,
		"medium": "oil"
	},
	{
		"title": "Sunday Stroll on St. Sebastian",
		"imageUrl": "http://jodyart.co.za/_include/img/work/full/A%20Sunday%20Stroll%20in%20St%20Sebastian.jpg",
		"thumbnailUrl": "http://jodyart.co.za/_include/img/work/thumbs/A-Sunday-Stroll-in-St-Sebastian.jpg",
		"width": 80,
		"height": 100,
		"medium": "oil"
	},
	{
		"title": "Gina",
		"imageUrl": "http://jodyart.co.za/_include/img/work/full/Gina.jpg",
		"thumbnailUrl": "http://jodyart.co.za/_include/img/work/thumbs/Gina.jpg",
		"width": 100,
		"height": 120,
		"medium": "oil"
	},
	{
		"title": "Huge Tyson",
		"imageUrl": "http://jodyart.co.za/_include/img/work/full/Tyson-with-attitude.jpg",
		"thumbnailUrl": "http://jodyart.co.za/_include/img/work/thumbs/Tyson-with-attitude.jpg",
		"width": 100,
		"height": 120,
		"medium": "oil"
	},
	{
		"title": "Tyson with Attitude",
		"imageUrl": "http://jodyart.co.za/_include/img/work/full/Money-Mayweather.jpg",
		"thumbnailUrl": "http://jodyart.co.za/_include/img/work/thumbs/Money-Mayweather.jpg",
		"width": 100,
		"height": 120,
		"medium": "oil"
	},
	{
		"title": "Money Mayweather",
		"imageUrl": "http://jodyart.co.za/_include/img/work/full/Cigar-Man.jpg",
		"thumbnailUrl": "http://jodyart.co.za/_include/img/work/thumbs/Cigar-Man.jpg",
		"width": 100,
		"height": 120,
		"medium": "oil"
	},
	{
		"title": "Cigar Man",
		"imageUrl": "http://jodyart.co.za/_include/img/work/full/Sleazy-man-and-Chick.jpg",
		"thumbnailUrl": "http://jodyart.co.za/_include/img/work/thumbs/Sleazy-man-and-Chick.jpg",
		"width": 80,
		"height": 100,
		"medium": "oil"
	},
	{
		"title": "Sleaze Man and Chick",
		"imageUrl": "http://jodyart.co.za/_include/img/work/full/red-waist-coated-trumpeterNo5.jpg",
		"thumbnailUrl": "http://jodyart.co.za/_include/img/work/thumbs/red-waist-coated-trumpeterNo5.jpg",
		"width": 80,
		"height": 100,
		"medium": "oil"
	},
	{
		"title": "Red Waistcoated Trumpter",
		"imageUrl": "http://jodyart.co.za/_include/img/work/full/Green-trumpeter.jpg",
		"thumbnailUrl": "http://jodyart.co.za/_include/img/work/thumbs/Green-trumpeter.jpg",
		"width": 60,
		"height": 70,
		"medium": "oil"
	},
	{
		"title": "Green Trumpeter",
		"imageUrl": "http://jodyart.co.za/_include/img/work/full/Dice-Man-no32.jpg",
		"thumbnailUrl": "http://jodyart.co.za/_include/img/work/thumbs/Dice-Man-no32.jpg",
		"width": 60,
		"height": 70,
		"medium": "oil"
	},
	{
		"title": "Dice Man",
		"imageUrl": "http://jodyart.co.za/_include/img/work/full/Casino-Babe.jpg",
		"thumbnailUrl": "http://jodyart.co.za/_include/img/work/thumbs/Casino-Babe.jpg",
		"width": 90,
		"height": 110,
		"medium": "oil"
	},
	{
		"title": "Casino Babe",
		"imageUrl": "http://jodyart.co.za/_include/img/work/full/red-carpet-affair.jpg",
		"thumbnailUrl": "http://jodyart.co.za/_include/img/work/thumbs/red-carpet-affair.jpg",
		"width": 90,
		"height": 110,
		"medium": "oil"
	},
	{
		"title": "Red Carpet Affair",
		"imageUrl": "http://jodyart.co.za/_include/img/work/full/Morning-Stretch.jpg",
		"thumbnailUrl": "http://jodyart.co.za/_include/img/work/thumbs/Morning-Stretch.jpg",
		"width": 80,
		"height": 100,
		"medium": "oil"
	},
	{
		"title": "Morning Stretch",
		"imageUrl": "http://jodyart.co.za/_include/img/work/full/Nearly-dressed.jpg",
		"thumbnailUrl": "http://jodyart.co.za/_include/img/work/thumbs/Nearly-dressed.jpg",
		"width": 80,
		"height": 100,
		"medium": "oil"
	},
	{
		"title": "Nearly Dressed",
		"imageUrl": "http://jodyart.co.za/_include/img/work/full/Girl-by-the-window.jpg",
		"thumbnailUrl": "http://jodyart.co.za/_include/img/work/thumbs/Girl-by-the-window.jpg",
		"width": 120,
		"height": 100,
		"medium": "oil"
	},
	{
		"title": "Girl by the Window",
		"imageUrl": "http://jodyart.co.za/_include/img/work/full/Girl-with-the-pearls.jpg",
		"thumbnailUrl": "http://jodyart.co.za/_include/img/work/thumbs/Girl-with-the-pearls.jpg",
		"width": 120,
		"height": 100,
		"medium": "oil"
	},
	{
		"title": "Girl with Pearls",
		"imageUrl": "http://jodyart.co.za/_include/img/work/full/image-01-full.jpg",
		"thumbnailUrl": "http://jodyart.co.za/_include/img/work/thumbs/image-01.jpg",
		"width": 91,
		"height": 76,
		"medium": "oil"
	},
	{
		"title": "Moaner Lisa",
		"imageUrl": "http://jodyart.co.za/_include/img/work/full/Golden-Bikini.jpg",
		"thumbnailUrl": "http://jodyart.co.za/_include/img/work/thumbs/Golden-Bikini.jpg",
		"width": 91,
		"height": 76,
		"medium": "oil"
	},
	{
		"title": "Golden Bikini",
		"imageUrl": "http://jodyart.co.za/_include/img/work/full/White-bikini-girl.jpg",
		"thumbnailUrl": "http://jodyart.co.za/_include/img/work/thumbs/White-bikini-girl.jpg",
		"width": 90,
		"height": 60,
		"medium": "oil"
	},
	{
		"title": "White Bikini Girl",
		"imageUrl": "http://jodyart.co.za/_include/img/work/full/Water-babe.jpg",
		"thumbnailUrl": "http://jodyart.co.za/_include/img/work/thumbs/Water-babe.jpg",
		"width": 90,
		"height": 60,
		"medium": "oil"
	},
	{
		"title": "Water Babe",
		"imageUrl": "http://jodyart.co.za/_include/img/work/full/MissLira.jpg",
		"thumbnailUrl": "http://jodyart.co.za/_include/img/work/thumbs/MissLira.jpg",
		"width": 160,
		"height": 90,
		"medium": "oil"
	},
	{
		"title": "Miss Lira",
		"imageUrl": "http://jodyart.co.za/_include/img/work/full/SimpheweDana.jpg",
		"thumbnailUrl": "http://jodyart.co.za/_include/img/work/thumbs/SimpheweDana.jpg",
		"width": 160,
		"height": 90,
		"medium": "oil"
	},
	{
		"title": "Simphewe Dana",
		"imageUrl": "http://jodyart.co.za/_include/img/work/full/The-Boss-Bruce-in-Soweto.jpg",
		"thumbnailUrl": "http://jodyart.co.za/_include/img/work/thumbs/The-Boss-Bruce-in-Soweto.jpg",
		"width": 90,
		"height": 60,
		"medium": "oil"
	},
	{
		"title": "The Boss Bruce",
		"imageUrl": "http://jodyart.co.za/_include/img/work/full/B-B-King.jpg",
		"thumbnailUrl": "http://jodyart.co.za/_include/img/work/thumbs/B-B-King.jpg",
		"width": 90,
		"height": 60,
		"medium": "oil"
	},
	{
		"title": "BB King",
		"imageUrl": "http://jodyart.co.za/_include/img/work/full/Unathi.jpg",
		"thumbnailUrl": "http://jodyart.co.za/_include/img/work/thumbs/Unathi.jpg",
		"width": 61,
		"height": 50,
		"medium": "oil"
	},
	{
		"title": "Unathi",
		"imageUrl": "http://jodyart.co.za/_include/img/work/full/Johnny-Clegg.jpg",
		"thumbnailUrl": "http://jodyart.co.za/_include/img/work/thumbs/Johnny-Clegg.jpg",
		"width": 61,
		"height": 50,
		"medium": "oil"
	},
	{
		"title": "Johnny Clegg",
		"imageUrl": "http://jodyart.co.za/_include/img/work/full/Lucky-Dube.jpg",
		"thumbnailUrl": "http://jodyart.co.za/_include/img/work/thumbs/Lucky-Dube.jpg",
		"width": 58,
		"height": 50,
		"medium": "oil"
	},
	{
		"title": "Lucky Dube",
		"imageUrl": "http://jodyart.co.za/_include/img/work/full/Lucky-Dube2.jpg",
		"thumbnailUrl": "http://jodyart.co.za/_include/img/work/thumbs/Lucky-Dube2.jpg",
		"width": 58,
		"height": 50,
		"medium": "oil"
	},
	{
		"title": "Lucky Dube II",
		"imageUrl": "http://jodyart.co.za/_include/img/work/full/Didi.jpg",
		"thumbnailUrl": "http://jodyart.co.za/_include/img/work/thumbs/Didi.jpg",
		"width": 67,
		"height": 51,
		"medium": "oil"
	},
	{
		"title": "Didi",
		"imageUrl": "http://jodyart.co.za/_include/img/work/full/Nolu.jpg",
		"thumbnailUrl": "http://jodyart.co.za/_include/img/work/thumbs/Nolu.jpg",
		"width": 67,
		"height": 51,
		"medium": "oil"
	},
	{
		"title": "Nolu",
		"imageUrl": "http://jodyart.co.za/_include/img/work/full/Bakang.jpg",
		"thumbnailUrl": "http://jodyart.co.za/_include/img/work/thumbs/Bakang.jpg",
		"width": 145,
		"height": 60,
		"medium": "oil"
	},
	{
		"title": "Bakang",
		"imageUrl": "http://jodyart.co.za/_include/img/work/full/Jabu.jpg",
		"thumbnailUrl": "http://jodyart.co.za/_include/img/work/thumbs/Jabu.jpg",
		"width": 145,
		"height": 60,
		"medium": "oil"
	},
	{
		"title": "Jabu",
		"imageUrl": "http://jodyart.co.za/_include/img/work/full/Brenda-Fassie.jpg",
		"thumbnailUrl": "http://jodyart.co.za/_include/img/work/thumbs/Brenda-Fassie.jpg",
		"width": 120,
		"height": 60,
		"medium": "oil"
	},
	{
		"title": "Brenda Fassie",
		"imageUrl": "http://jodyart.co.za/_include/img/work/full/roses.jpg",
		"thumbnailUrl": "http://jodyart.co.za/_include/img/work/thumbs/roses.jpg",
		"width": 120,
		"height": 60,
		"medium": "oil"
	},
	{
		"title": "Roses",
		"imageUrl": "http://jodyart.co.za/_include/img/work/full/botanic-1.jpg",
		"thumbnailUrl": "http://jodyart.co.za/_include/img/work/thumbs/botanic-1.jpg",
		"width": 100,
		"height": 80,
		"medium": "oil"
	},
	{
		"title": "Botanic 1",
		"imageUrl": "http://jodyart.co.za/_include/img/work/full/Botanic-2.jpg",
		"thumbnailUrl": "http://jodyart.co.za/_include/img/work/thumbs/Botanic-2.jpg",
		"width": 100,
		"height": 80,
		"medium": "oil"
	},
	{
		"title": "Botanic 2",
		"imageUrl": "http://jodyart.co.za/_include/img/work/full/Orchids.jpg",
		"thumbnailUrl": "http://jodyart.co.za/_include/img/work/thumbs/Orchids.jpg",
		"width": 90,
		"height": 60,
		"medium": "oil"
	},
	{
		"title": "Orchids",
		"imageUrl": "http://jodyart.co.za/_include/img/work/full/image-04-full.jpg",
		"thumbnailUrl": "http://jodyart.co.za/_include/img/work/thumbs/image-04.jpg",
		"width": 90,
		"height": 60,
		"medium": "oil"
	},
	{
		"title": "Contemplation",
		"imageUrl": "http://jodyart.co.za/_include/img/work/full/image-05-full.jpg",
		"thumbnailUrl": "http://jodyart.co.za/_include/img/work/thumbs/image-05.jpg",
		"width": 120,
		"height": 63,
		"medium": "oil"
	},
	{
		"title": "Soussesvlei",
		"imageUrl": "http://jodyart.co.za/_include/img/work/full/image-06-full.jpg",
		"thumbnailUrl": "http://jodyart.co.za/_include/img/work/thumbs/image-06.jpg",
		"width": 120,
		"height": 63,
		"medium": "oil"
	},
	{
		"title": "Ballet Dancers in Wings",
		"imageUrl": "http://jodyart.co.za/_include/img/work/full/image-07-full.jpg",
		"thumbnailUrl": "http://jodyart.co.za/_include/img/work/thumbs/image-07.jpg",
		"width": 110,
		"height": 90,
		"medium": "oil"
	},
	{
		"title": "Girl in Dead Sea",
		"imageUrl": "http://jodyart.co.za/_include/img/work/full/image-08-full.jpg",
		"thumbnailUrl": "http://jodyart.co.za/_include/img/work/thumbs/image-08.jpg",
		"width": 110,
		"height": 90,
		"medium": "oil"
	},
	{
		"title": "Girl in Dead Sea II",
		"imageUrl": "http://jodyart.co.za/_include/img/work/full/image-09-full.jpg",
		"thumbnailUrl": "http://jodyart.co.za/_include/img/work/thumbs/image-09.jpg",
		"width": 90,
		"height": 90,
		"medium": "oil"
	},
	{
		"title": "Girl in H2O",
		"imageUrl": "http://jodyart.co.za/_include/img/work/full/image-10-full.jpg",
		"thumbnailUrl": "http://jodyart.co.za/_include/img/work/thumbs/image-10.jpg",
		"width": 90,
		"height": 90,
		"medium": "oil"
	},
	{
		"title": "Girl in Turquoise",
		"imageUrl": "http://jodyart.co.za/_include/img/work/full/image-12-full.jpg",
		"thumbnailUrl": "http://jodyart.co.za/_include/img/work/thumbs/image-12.jpg",
		"width": 80,
		"height": 54,
		"medium": "oil"
	},
	{
		"title": "Picking up Shells",
		"imageUrl": "http://jodyart.co.za/_include/img/work/full/image-13-full.jpg",
		"thumbnailUrl": "http://jodyart.co.za/_include/img/work/thumbs/image-13.jpg",
		"width": 80,
		"height": 54,
		"medium": "oil"
	},
	{
		"title": "Girl in bathroom and white chair",
		"imageUrl": "http://jodyart.co.za/_include/img/work/full/image-14-full.jpg",
		"thumbnailUrl": "http://jodyart.co.za/_include/img/work/thumbs/image-14.jpg",
		"width": 100,
		"height": 80,
		"medium": "oil"
	},
	{
		"title": "Girl in bubbles",
		"imageUrl": "http://jodyart.co.za/_include/img/work/full/image-15-full.jpg",
		"thumbnailUrl": "http://jodyart.co.za/_include/img/work/thumbs/image-15.jpg",
		"width": 100,
		"height": 80,
		"medium": "oil"
	},
	{
		"title": "Namibian Plains",
		"imageUrl": "http://jodyart.co.za/_include/img/work/full/image-16-full.jpg",
		"thumbnailUrl": "http://jodyart.co.za/_include/img/work/thumbs/image-16.jpg",
		"width": 100,
		"height": 80,
		"medium": "oil"
	},
	{
		"title": "Dancers Soaring",
		"imageUrl": "http://jodyart.co.za/_include/img/work/full/image-17-full.jpg",
		"thumbnailUrl": "http://jodyart.co.za/_include/img/work/thumbs/image-17.jpg",
		"width": 100,
		"height": 80,
		"medium": "oil"
	},
	{
		"title": "Undressing",
		"imageUrl": "http://jodyart.co.za/_include/img/work/full/image-18-full.jpg",
		"thumbnailUrl": "http://jodyart.co.za/_include/img/work/thumbs/image-18.jpg",
		"width": 100,
		"height": 80,
		"medium": "oil"
	},
	{
		"title": "Yen or Zen",
		"imageUrl": "http://jodyart.co.za/_include/img/work/full/image-19-full.jpg",
		"thumbnailUrl": "http://jodyart.co.za/_include/img/work/thumbs/image-19.jpg",
		"width": 100,
		"height": 80,
		"medium": "oil"
	},
	{
		"title": "Bad Hair Day",
		"imageUrl": "http://jodyart.co.za/_include/img/work/full/image-20-full.jpg",
		"thumbnailUrl": "http://jodyart.co.za/_include/img/work/thumbs/image-20.jpg",
		"width": 100,
		"height": 80,
		"medium": "oil"
	},
	{
		"title": "Transkei Man",
		"imageUrl": "http://jodyart.co.za/_include/img/work/full/image-21-full.jpg",
		"thumbnailUrl": "http://jodyart.co.za/_include/img/work/thumbs/image-21.jpg",
		"width": 100,
		"height": 80,
		"medium": "oil"
	},
	{
		"title": "Naked Woman in Black Skirt",
		"imageUrl": "http://jodyart.co.za/_include/img/work/full/image-22-full.jpg",
		"thumbnailUrl": "http://jodyart.co.za/_include/img/work/thumbs/image-22.jpg",
		"width": 47,
		"height": 39,
		"medium": "oil"
	},
	{
		"title": "Magenta Orchids",
		"imageUrl": "http://jodyart.co.za/_include/img/work/full/image-23-full.jpg",
		"thumbnailUrl": "http://jodyart.co.za/_include/img/work/thumbs/image-23.jpg",
		"width": 47,
		"height": 39,
		"medium": "oil"
	},
	{
		"title": "Pink Orchid in White",
		"imageUrl": "http://jodyart.co.za/_include/img/work/full/image-24-full.jpg",
		"thumbnailUrl": "http://jodyart.co.za/_include/img/work/thumbs/image-24.jpg",
		"width": 110,
		"height": 80,
		"medium": "oil"
	},
	{
		"title": "Green Leafed Orchid",
		"imageUrl": "http://jodyart.co.za/_include/img/work/full/image-25-full.jpg",
		"thumbnailUrl": "http://jodyart.co.za/_include/img/work/thumbs/image-25.jpg",
		"width": 110,
		"height": 80,
		"medium": "oil"
	},
	{
		"title": "Blue Aloes",
		"imageUrl": "http://jodyart.co.za/_include/img/work/full/image-26-full.jpg",
		"thumbnailUrl": "http://jodyart.co.za/_include/img/work/thumbs/image-26.jpg",
		"width": 76,
		"height": 61,
		"medium": "oil"
	},
	{
		"title": "Aloe Hello",
		"imageUrl": "http://jodyart.co.za/_include/img/work/full/image-27-full.jpg",
		"thumbnailUrl": "http://jodyart.co.za/_include/img/work/thumbs/image-27.jpg",
		"width": 76,
		"height": 61,
		"medium": "oil"
	},
	{
		"title": "Proteas",
		"imageUrl": "http://jodyart.co.za/_include/img/work/full/image-28-full.jpg",
		"thumbnailUrl": "http://jodyart.co.za/_include/img/work/thumbs/image-28.jpg",
		"width": 76,
		"height": 61,
		"medium": "oil"
	},
	{
		"title": "Winter Yakka",
		"imageUrl": "http://jodyart.co.za/_include/img/work/full/image-30-full.jpg",
		"thumbnailUrl": "http://jodyart.co.za/_include/img/work/thumbs/image-30.jpg",
		"width": 76,
		"height": 61,
		"medium": "oil"
	}
]
